smoltok-0.1.1.dist-info/METADATA
smoltok-0.1.1.dist-info/WHEEL
smoltok/__init__.py
smoltok/__init__.pyi
smoltok/py.typed
smoltok/smoltok.abi3.so
smoltok-0.1.1.dist-info/RECORD
